opt/__init__.py
opt/abstract_optimizer.py
opt/adadelta.py
opt/adagrad.py
opt/adaptive_moment_estimation.py
opt/ant_colony.py
opt/artificial_fish_swarm_algorithm.py
opt/augmented_lagrangian_method.py
opt/bat_algorithm.py
opt/bee_algorithm.py
opt/benchmark/__init__.py
opt/benchmark/functions.py
opt/cat_swarm_optimization.py
opt/cma_es.py
opt/colliding_bodies_optimization.py
opt/cross_entropy_method.py
opt/cuckoo_search.py
opt/cultural_algorithm.py
opt/differential_evolution.py
opt/eagle_strategy.py
opt/estimation_of_distribution_algorithm.py
opt/firefly_algorithm.py
opt/genetic_algorithm.py
opt/glowworm_swarm_optimization.py
opt/grey_wolf_optimizer.py
opt/harmony_search.py
opt/hill_climbing.py
opt/imperialist_competitive_algorithm.py
opt/linear_discriminant_analysis.py
opt/particle_filter.py
opt/particle_swarm.py
opt/parzen_tree_stimator.py
opt/shuffled_frog_leaping_algorithm.py
opt/simulated_annealing.py
opt/sine_cosine_algorithm.py
opt/squirrel_search.py
opt/stochastic_diffusion_search.py
opt/stochastic_fractal_search.py
opt/successive_linear_programming.py
opt/tabu_search.py
opt/variable_depth_search.py
opt/variable_neighbourhood_search.py
opt/very_large_scale_neighborhood_search.py
opt/whale_optimization_algorithm.py
useful_optimizer-0.1.2.dist-info/LICENSE
useful_optimizer-0.1.2.dist-info/METADATA
useful_optimizer-0.1.2.dist-info/WHEEL
useful_optimizer-0.1.2.dist-info/RECORD
