Metadata-Version: 2.1
Name: useful-optimizer
Version: 0.1.2
Summary: A dedicated set of optimization algorithms for numeric problems.
License: MIT
Author: Anselm Hahn
Author-email: Anselm.Hahn@gmail.com
Requires-Python: >=3.10,<3.13
Classifier: License :: OSI Approved :: MIT License
Classifier: Programming Language :: Python :: 3
Classifier: Programming Language :: Python :: 3.10
Classifier: Programming Language :: Python :: 3.11
Classifier: Programming Language :: Python :: 3.12
Requires-Dist: numpy (>=1.26.4,<2.0.0)
Requires-Dist: scikit-learn (>=1.5.1,<2.0.0)
Requires-Dist: scipy (>=1.12.0,<2.0.0)
